pyrosequel/__init__.py
pyrosequel/column.py
pyrosequel/model.py
pyrosequel/query.py
pyrosequel/sqlfn.py
pyrosequel/sqlitedb.py
pyrosequel-0.1.2.dist-info/LICENSE
pyrosequel-0.1.2.dist-info/METADATA
pyrosequel-0.1.2.dist-info/WHEEL
pyrosequel-0.1.2.dist-info/top_level.txt
pyrosequel-0.1.2.dist-info/RECORD
