Metadata-Version: 2.1
Name: pyrosequel
Version: 0.1.2
Summary: PyroSequel, advanced SQL querying
Home-page: https://github.com/geckwwo/pyrosequel
Author: geckwwo
Project-URL: Bug Tracker, https://github.com/geckwwo/pyrosequel/issues
Project-URL: repository, https://github.com/geckwwo/pyrosequel
Classifier: Programming Language :: Python :: 3
Classifier: License :: OSI Approved :: BSD License
Classifier: Operating System :: OS Independent
Requires-Python: >=3.10
License-File: LICENSE
